wbjdbc/__init__.py
wbjdbc/jvm.py
wbjdbc/resources/dependencies/jpype1-1.5.1-cp311-cp311-macosx_10_9_universal2.whl
wbjdbc/resources/dependencies/jpype1-1.5.1-cp311-cp311-manylinux_2_17_x86_64.manylinux2014_x86_64.whl
wbjdbc/resources/dependencies/jpype1-1.5.1-cp311-cp311-win_amd64.whl
wbjdbc/resources/dependencies/jpype1-1.5.1-cp312-cp312-macosx_10_9_universal2.whl
wbjdbc/resources/dependencies/jpype1-1.5.1-cp312-cp312-manylinux_2_17_x86_64.manylinux2014_x86_64.whl
wbjdbc/resources/dependencies/jpype1-1.5.1-cp312-cp312-win_amd64.whl
wbjdbc/resources/maven/com.ibm.informix/jdbc-4.50.10.1.jar
wbjdbc/resources/maven/com.ibm.informix/jdbc-4.50.10.1.pom
wbjdbc/resources/maven/org.mongodb/bson-3.8.0.jar
wbjdbc/resources/maven/org.mongodb/bson-3.8.0.pom
wbjdbc/resources/server/classes.jsa
wbjdbc/resources/server/classes_nocoops.jsa
wbjdbc/resources/server/jvm.dll
wbjdbc/resources/server/jdk-17.0.2/COPYRIGHT
wbjdbc/resources/server/jdk-17.0.2/LICENSE
wbjdbc/resources/server/jdk-17.0.2/README
wbjdbc/resources/server/jdk-17.0.2/release
wbjdbc/resources/server/jdk-17.0.2/bin/WinFallbackLookup.dll
wbjdbc/resources/server/jdk-17.0.2/bin/api-ms-win-core-console-l1-1-0.dll
wbjdbc/resources/server/jdk-17.0.2/bin/api-ms-win-core-console-l1-2-0.dll
wbjdbc/resources/server/jdk-17.0.2/bin/api-ms-win-core-datetime-l1-1-0.dll
wbjdbc/resources/server/jdk-17.0.2/bin/api-ms-win-core-debug-l1-1-0.dll
wbjdbc/resources/server/jdk-17.0.2/bin/api-ms-win-core-errorhandling-l1-1-0.dll
wbjdbc/resources/server/jdk-17.0.2/bin/api-ms-win-core-file-l1-1-0.dll
wbjdbc/resources/server/jdk-17.0.2/bin/api-ms-win-core-file-l1-2-0.dll
wbjdbc/resources/server/jdk-17.0.2/bin/api-ms-win-core-file-l2-1-0.dll
wbjdbc/resources/server/jdk-17.0.2/bin/api-ms-win-core-handle-l1-1-0.dll
wbjdbc/resources/server/jdk-17.0.2/bin/api-ms-win-core-heap-l1-1-0.dll
wbjdbc/resources/server/jdk-17.0.2/bin/api-ms-win-core-interlocked-l1-1-0.dll
wbjdbc/resources/server/jdk-17.0.2/bin/api-ms-win-core-libraryloader-l1-1-0.dll
wbjdbc-1.2.1.dist-info/licenses/LICENSE
wbjdbc-1.2.1.dist-info/METADATA
wbjdbc-1.2.1.dist-info/WHEEL
wbjdbc-1.2.1.dist-info/top_level.txt
wbjdbc-1.2.1.dist-info/RECORD
