Metadata-Version: 2.4
Name: wbjdbc
Version: 1.2.1
Summary: Library to simplify JDBC and JVM configuration for Informix and MongoDB
Home-page: https://github.com/wanderbatistaf/wbjdbc
Author: Wanderson Batista
Author-email: wanderfreitasb@gmail.com
License-File: LICENSE
Requires-Dist: jaydebeapi
Requires-Dist: JPype1>=1.3.0
Dynamic: author
Dynamic: author-email
Dynamic: description
Dynamic: description-content-type
Dynamic: home-page
Dynamic: license-file
Dynamic: requires-dist
Dynamic: summary
